MANIFEST.in
README.rst
setup.py
mathpixy/__init__.py
mathpixy/__main__.py
mathpixy/mathpixy.py
mathpixy.egg-info/PKG-INFO
mathpixy.egg-info/SOURCES.txt
mathpixy.egg-info/dependency_links.txt
mathpixy.egg-info/entry_points.txt
mathpixy.egg-info/top_level.txt