Metadata-Version: 1.0
Name: mathpixy
Version: 0.0.1.dev0
Summary: gui for mathpix
Home-page: https://github.com/ejmg/mathpixy
Author: elias julian marko garcia
Author-email: elias.jm.garcia@gmail.com
License: MIT
Platform: UNKNOWN
